flowers/__init__.py
flowers/extract_utils.py
flowers/file_utils.py
flowers/nlp_utils.py
flowers/prefix.py
flowers/translate.py
flowers-0.1.3.dist-info/METADATA
flowers-0.1.3.dist-info/WHEEL
flowers-0.1.3.dist-info/top_level.txt
flowers-0.1.3.dist-info/RECORD
