Metadata-Version: 2.1
Name: flowers
Version: 0.1.3
Summary: utils
Home-page: https://github.com/hgliyuhao/flower
Author: liyuhao
Author-email: 1241225413@qq.com
License: Apache License 2.0
Platform: UNKNOWN
Requires-Dist: pdfminer3k
Requires-Dist: requests
